Metadata-Version: 2.1
Name: weblate-vpatch
Version: 0.0.1
Summary: Weblate Version Patcher
Home-page: https://github.com/dgarana/weblate_vpatch
Author: David Garaña
License: UNKNOWN
Keywords: weblate version patcher
Platform: UNKNOWN
Classifier: Development Status :: 3 - Alpha
Classifier: Intended Audience :: Developers
Classifier: Topic :: Software Development :: Build Tools
Classifier: License :: OSI Approved :: MIT License
Classifier: Programming Language :: Python :: 2
Classifier: Programming Language :: Python :: 2.7
Classifier: Programming Language :: Python :: 3
Classifier: Programming Language :: Python :: 3.4
Classifier: Programming Language :: Python :: 3.5
Classifier: Programming Language :: Python :: 3.6
Classifier: Programming Language :: Python :: 3.7
